[
  {
    "id": "18012915056192026",
    "created_at": 1710150593,
    "text": "1000",
    "owner": {
      "id": "583933066",
      "is_verified": false,
      "profile_pic_url": "https://scontent-iev1-1.cdninstagram.com/v/t51.2885-19/383061052_702895995040398_6696218857754017368_n.jpg?stp=dst-jpg_s150x150&_nc_ht=scontent-iev1-1.cdninstagram.com&_nc_cat=106&_nc_ohc=cg-qNYCG1_kAX9N4XW9&edm=AMrZAGUBAAAA&ccb=7-5&oh=00_AfDPA0xGxLvn447PqtW_zKKwn8c-7IkNDhCbNVRzwJgGnA&oe=660DD6AC&_nc_sid=17eaee",
      "username": "a.lyona.sun"
    },
    "likes_count": 1,
    "answers": []
  },
  {
    "id": "17904645821945885",
    "created_at": 1710144322,
    "text": "700",
    "owner": {
      "id": "37868134208",
      "is_verified": false,
      "profile_pic_url": "https://scontent-iev1-1.cdninstagram.com/v/t51.2885-19/422836612_348849937920713_5977436494653157459_n.jpg?stp=dst-jpg_s150x150&_nc_ht=scontent-iev1-1.cdninstagram.com&_nc_cat=105&_nc_ohc=HHChDqxof7AAX8LHzhT&edm=AMrZAGUBAAAA&ccb=7-5&oh=00_AfATgZ8_TP3cZOJD-0Yt7VMIjpjvVKeeQRY_TFkTLzi-tw&oe=660DEFA1&_nc_sid=17eaee",
      "username": "95stepan"
    },
    "likes_count": 0,
    "answers": [
      {
        "id": 18030123526821445,
        "created_at": 1710151003,
        "text": "@95stepan \u043f\u0435\u0440\u0435\u0431\u0438\u0442\u043e\ud83d\udd28",
        "owner": {
          "id": "64655533308",
          "is_verified": false,
          "profile_pic_url": "https://scontent-iev1-1.cdninstagram.com/v/t51.2885-19/427666117_424880886632391_8456744437262568953_n.jpg?stp=dst-jpg_s150x150&_nc_ht=scontent-iev1-1.cdninstagram.com&_nc_cat=103&_nc_ohc=_K0p807vVTIAX9dldFK&edm=AMrZAGUBAAAA&ccb=7-5&oh=00_AfBqLd0QACBs_CiKbNGuYs3aKGsSnrvi72X84ZSCtwv1ZQ&oe=660E014F&_nc_sid=17eaee",
          "username": "kse_meeting_auction"
        },
        "likes_count": 0
      }
    ]
  },
  {
    "id": "18004487543457924",
    "created_at": 1710108685,
    "text": "500",
    "owner": {
      "id": "583933066",
      "is_verified": false,
      "profile_pic_url": "https://scontent-iev1-1.cdninstagram.com/v/t51.2885-19/383061052_702895995040398_6696218857754017368_n.jpg?stp=dst-jpg_s150x150&_nc_ht=scontent-iev1-1.cdninstagram.com&_nc_cat=106&_nc_ohc=cg-qNYCG1_kAX9N4XW9&edm=AMrZAGUBAAAA&ccb=7-5&oh=00_AfDPA0xGxLvn447PqtW_zKKwn8c-7IkNDhCbNVRzwJgGnA&oe=660DD6AC&_nc_sid=17eaee",
      "username": "a.lyona.sun"
    },
    "likes_count": 1,
    "answers": [
      {
        "id": 18050041654593569,
        "created_at": 1710145449,
        "text": "@a.lyona.sun \u043f\u0435\u0440\u0435\u0431\u0438\u0442\u043e\ud83d\udd28",
        "owner": {
          "id": "64655533308",
          "is_verified": false,
          "profile_pic_url": "https://scontent-iev1-1.cdninstagram.com/v/t51.2885-19/427666117_424880886632391_8456744437262568953_n.jpg?stp=dst-jpg_s150x150&_nc_ht=scontent-iev1-1.cdninstagram.com&_nc_cat=103&_nc_ohc=_K0p807vVTIAX9dldFK&edm=AMrZAGUBAAAA&ccb=7-5&oh=00_AfBqLd0QACBs_CiKbNGuYs3aKGsSnrvi72X84ZSCtwv1ZQ&oe=660E014F&_nc_sid=17eaee",
          "username": "kse_meeting_auction"
        },
        "likes_count": 0
      }
    ]
  },
  {
    "id": "18005112731377311",
    "created_at": 1710101818,
    "text": "100",
    "owner": {
      "id": "37868134208",
      "is_verified": false,
      "profile_pic_url": "https://scontent-iev1-1.cdninstagram.com/v/t51.2885-19/422836612_348849937920713_5977436494653157459_n.jpg?stp=dst-jpg_s150x150&_nc_ht=scontent-iev1-1.cdninstagram.com&_nc_cat=105&_nc_ohc=HHChDqxof7AAX8LHzhT&edm=AMrZAGUBAAAA&ccb=7-5&oh=00_AfATgZ8_TP3cZOJD-0Yt7VMIjpjvVKeeQRY_TFkTLzi-tw&oe=660DEFA1&_nc_sid=17eaee",
      "username": "95stepan"
    },
    "likes_count": 1,
    "answers": [
      {
        "id": 18324985441186214,
        "created_at": 1710108713,
        "text": "@95stepan \u043f\u0435\u0440\u0435\u0431\u0438\u0442\u043e\ud83d\udd28",
        "owner": {
          "id": "64655533308",
          "is_verified": false,
          "profile_pic_url": "https://scontent-iev1-1.cdninstagram.com/v/t51.2885-19/427666117_424880886632391_8456744437262568953_n.jpg?stp=dst-jpg_s150x150&_nc_ht=scontent-iev1-1.cdninstagram.com&_nc_cat=103&_nc_ohc=_K0p807vVTIAX9dldFK&edm=AMrZAGUBAAAA&ccb=7-5&oh=00_AfBqLd0QACBs_CiKbNGuYs3aKGsSnrvi72X84ZSCtwv1ZQ&oe=660E014F&_nc_sid=17eaee",
          "username": "kse_meeting_auction"
        },
        "likes_count": 0
      }
    ]
  }
]
